[{"id":"372010","alistPath":"https://bangumi.sakiko.top/Bangumi/狼与香辛料 行商邂逅贤狼","bgmUrl":"https://bangumi.tv/subject/372010","img":"//lain.bgm.tv/r/400/pic/cover/l/08/df/372010_KBWk9.jpg","name":"狼と香辛料 MERCHANT MEETS THE WISE WOLF","chineseName":"狼与香辛料 行商邂逅贤狼","episode":"25","date":"2024年4月1日","weekday":"星期一","score":"7.3","tagList":["TV","日本","奇幻","小说改","公路","2024年4月","轻小说改","狼与香辛料","旅行","治愈","Passione","恋爱","2024","轻改","续集","公路片","重制","未定档","经济","2024年","狼と香辛料","重制版","日常","さんぺい聖"],"aliasList":["狼与香辛料 MERCHANT MEETS THE WISE WOLF","Spice and Wolf: Merchant Meets the Wise Wolf","Ookami to Koushinryou: Merchant Meets the Wise Wolf"]},{"id":"411276","alistPath":"https://bangumi.sakiko.top/Bangumi/夜樱家的大作战","bgmUrl":"https://bangumi.tv/subject/411276","img":"//lain.bgm.tv/r/400/pic/cover/l/9d/9a/411276_Kzyt0.jpg","name":"夜桜さんちの大作戦","chineseName":"夜樱家的大作战","episode":"27","date":"2024年4月7日","weekday":"星期日","score":"6.0","tagList":["TV","恋爱","漫画改","战斗","2024年4月","SILVERLINK.","奇幻","2024","漫改","搞笑","集英社","JUMP","本渡楓","2024年","校园","日本动画","超能力","幼驯染","纯爱","2020-2029","凑未来"],"aliasList":["Mission of Yozakura Family","Mission: Yozakura Family","Yozakura-san Chi no Daisakusen"]},{"id":"461338","alistPath":"https://bangumi.sakiko.top/Bangumi/良禽不择木","bgmUrl":"https://bangumi.tv/subject/461338","img":"//lain.bgm.tv/r/400/pic/cover/l/6b/ef/461338_mfpKk.jpg","name":"烏は主を選ばない","chineseName":"乌鸦不择主","episode":"20","date":"2024年4月6日","weekday":"星期六","score":"7.1","tagList":["悬疑","TV","日本","奇幻","剧情","小说改","宫廷","2024年4月","StudioPierrot","2024","轻改","入野自由","轻小说改","和风","ぴえろ","小丑社","PIERROT","战斗","2024年","腐向","2023年4月","TVA","2024年7月","京極義昭","京极义昭"],"aliasList":["良禽不择木","乌鸦姬不选择主人","Karasu wa Aruji wo Erabanai","Yatagarasu: The Raven Does Not Choose Its Master"]},{"id":"444339","alistPath":"https://bangumi.sakiko.top/Bangumi/杀手寓言","bgmUrl":"https://bangumi.tv/subject/444339","img":"//lain.bgm.tv/r/400/pic/cover/l/4c/ce/444339_91FQX.jpg","name":"ザ・ファブル","chineseName":"杀手寓言","episode":"25","date":"2024年4月6日","weekday":"星期六","score":"6.7","tagList":["搞笑","TV","日本","漫画改","战斗","日常","剧情","2024年4月","手塚PRODUCTION","2024","漫改","杀手","高桥良辅","黑道","日本动画","2024年","手冢Production","2024年7月","半年番","推荐","TVA","泽城美雪","杀手寓言"],"aliasList":["The Fable"]},{"id":"407573","alistPath":"https://bangumi.sakiko.top/Bangumi/关于我转生变成史莱姆这档事","bgmUrl":"https://bangumi.tv/subject/407573","img":"//lain.bgm.tv/r/400/pic/cover/l/f0/f4/407573_993Vy.jpg","name":"転生したらスライムだった件 第3期","chineseName":"关于我转生变成史莱姆这档事 第三季","episode":"24","date":"2024年4月5日","weekday":"星期五","score":"5.6","tagList":["TV","奇幻","战斗","异世界","2024年4月","轻小说改","关于我转生变成史莱姆这档事","轻改","8bit","2024","穿越","魔法","龙傲天","续作","日常","小说改","续集","后宫","动画","搞笑","2024年","日漫","萌王","种田","2020s","漫改","利姆露谈治国理政","开会"],"aliasList":["Tensei Shitara Slime Datta Ken (2024)","That Time I Got Reincarnated as a Slime (2024)","Tensei Shitara Slime Datta Ken 3rd Season","That Time I Got Reincarnated as a Slime Season 3"]},{"id":"386809","alistPath":"https://bangumi.sakiko.top/Bangumi/【我推的孩子】","bgmUrl":"https://bangumi.tv/subject/386809","img":"//lain.bgm.tv/r/400/pic/cover/l/98/5e/386809_1yR81.jpg","name":"【推しの子】","chineseName":"【我推的孩子】","episode":"11","date":"2023年4月12日","weekday":"星期三","score":"7.5","tagList":["TV","恋爱","日本","漫画改","偶像","动画工房","2023年4月","赤坂明","悬疑","漫改","2023","動画工房","田中仁","转生","党争","复仇","我推的孩子","搞笑","奇幻","2023年","校园","日常","高桥李依","后宫","职场","平牧大辅","平牧大輔","平山宽菜"],"aliasList":["Oshi no Ko"]},{"id":"443428","alistPath":"https://bangumi.sakiko.top/Bangumi/【我推的孩子】","bgmUrl":"https://bangumi.tv/subject/443428","img":"//lain.bgm.tv/r/400/pic/cover/l/d1/1c/443428_FIhFu.jpg","name":"【推しの子】 第2期","chineseName":"【我推的孩子】 第二季","episode":"13","date":"2024年7月3日","weekday":"星期三","score":"7.4","tagList":["TV","恋爱","漫画改","偶像","动画工房","2024年7月","赤坂明","【我推的孩子】","漫改","2024","悬疑","续作","复仇","续集","我推的孩子","党争","田中仁","未定档","動画工房","2024年","日常","日本","职场","后宫","奇幻","季番","平牧大輔"],"aliasList":["【推しの子】 シーズン2","Oshi no Ko 2nd Season","\"Oshi no Ko\" 2"]},{"id":"470874","alistPath":"https://bangumi.sakiko.top/Bangumi/腼腆英雄 东京夺还篇","bgmUrl":"https://bangumi.tv/subject/470874","img":"//lain.bgm.tv/r/400/pic/cover/l/cd/89/470874_zSyEG.jpg","name":"SHY 東京奪還編","chineseName":"腼腆英雄 东京夺还篇","episode":"12","date":"2024年7月1日","weekday":"星期一","score":"5.5","tagList":["TV","漫画改","2024年7月","8bit","百合","2024","漫改","战斗","安藤正臣","東山奈央","2024年","奇幻","TVA","未定档","日本动画","腼腆英雄","SHY"],"aliasList":["Shy: Tokyo Dakkan Hen","Shy (2024)","SHY 第2期","シャイ 第2期","腼腆英雄 第二季","SHY 腼腆英雄 第二季"]},{"id":"424883","alistPath":"https://bangumi.sakiko.top/Bangumi/不时用俄语小声说真心话的邻桌艾莉同学","bgmUrl":"https://bangumi.tv/subject/424883","img":"//lain.bgm.tv/r/400/pic/cover/l/7c/8e/424883_BpzVb.jpg","name":"時々ボソッとロシア語でデレる隣のアーリャさん","chineseName":"不时轻声地以俄语遮羞的邻座艾莉同学","episode":"12","date":"2024年7月3日","weekday":"星期三","score":"5.8","tagList":["校园","TV","恋爱","小说改","动画工房","2024年7月","轻小说改","轻改","上坂すみれ","2024","日常","搞笑","2024年4月","動画工房","青春","后宫","党争","厕纸","2024年","日本","科幻","妹妹","恋爱喜剧","福利","未确定","TVA","俄语","伊藤良太"],"aliasList":["不时用俄语小声说真心话的邻桌艾莉同学","Tokidoki Bosotto Russia-go de Dereru Tonari no Alya-san","Alya Sometimes Hides Her Feelings in Russian"]},{"id":"397604","alistPath":"https://bangumi.sakiko.top/Bangumi/亚托莉 -我挚爱的时光-","bgmUrl":"https://bangumi.tv/subject/397604","img":"//lain.bgm.tv/r/400/pic/cover/l/66/6d/397604_TgJ63.jpg","name":"ATRI -My Dear Moments-","chineseName":"亚托莉 -我挚爱的时光-","episode":"13","date":"2024年7月13日","weekday":"星期六","score":"6.3","tagList":["TV","恋爱","游戏改","GAL改","2024年7月","花田十辉","TROYCA","治愈","催泪","2024","科幻","2023","未定档","花田十輝","机器人","2024年","未确定","2023年","末世","原创","游改","日常","奇幻","7月","TVA","萝莉","ATRI","加藤诚","加藤誠"],"aliasList":[]},{"id":"484761","alistPath":"https://bangumi.sakiko.top/Bangumi/鹿乃子乃子乃子虎视眈眈","bgmUrl":"https://bangumi.tv/subject/484761","img":"//lain.bgm.tv/r/400/pic/cover/l/b1/7b/484761_r83E8.jpg","name":"しかのこのこのここしたんたん","chineseName":"鹿乃子乃子乃子虎视眈眈","episode":"12","date":"2024年7月7日","weekday":"星期日","score":"5.4","tagList":["搞笑","校园","TV","日本","漫画改","轻百合","2024年7月","WITSTUDIO","沙雕","百合","日常","2024","漫改","欢乐","太田雅彦","电波","抽象","奇幻","2024年","萌","无厘头","WIT_STUDIO","轻百","季番","神经"],"aliasList":["鹿乃子大摇大摆虎视眈眈","Shikanoko Nokonoko Koshitantan","My Deer Friend Nokotan"]},{"id":"393037","alistPath":"https://bangumi.sakiko.top/Bangumi/义妹生活","bgmUrl":"https://bangumi.tv/subject/393037","img":"//lain.bgm.tv/r/400/pic/cover/l/40/01/393037_I7mvN.jpg","name":"義妹生活","chineseName":"义妹生活","episode":"12","date":"2024年7月4日","weekday":"星期四","score":"7.2","tagList":["TV","恋爱","日本","日常","小说改","2024年7月","轻小说改","兄妹","studiodeen","校园","轻改","2024","妹系","2024年","文艺","青春","治愈","妹妹","纯爱","空气系","スタジオディーン","上野壮大","义妹生活系列"],"aliasList":["Days with My Stepsister","Gimai Seikatsu"]},{"id":"482776","alistPath":"https://bangumi.sakiko.top/Bangumi/我的妻子没有感情","bgmUrl":"https://bangumi.tv/subject/482776","img":"//lain.bgm.tv/r/400/pic/cover/l/ce/50/482776_G98Y9.jpg","name":"僕の妻は感情がない","chineseName":"我的妻子没有感情","episode":"12","date":"2024年7月2日","weekday":"星期二","score":"6.1","tagList":["TV","恋爱","日本","2024年7月","漫画改","机器人","手塚PRODUCTION","科幻","漫改","日常","2024","手冢Production","治愈","2024年","搞笑","萝卜","漫画改编","人性","日本动画","温馨","TVA","TMS","吉村文宏"],"aliasList":["我的妻子不具感情","Boku no Tsuma wa Kanjou ga Nai","My Wife Has No Emotion"]},{"id":"444046","alistPath":"https://bangumi.sakiko.top/Bangumi/异世界自杀小队","bgmUrl":"https://bangumi.tv/subject/444046","img":"//lain.bgm.tv/r/400/pic/cover/l/00/ae/444046_9b5bM.jpg","name":"異世界スーサイド・スクワッド","chineseName":"异世界自杀小队","episode":"10","date":"2024年7月5日","weekday":"星期五","score":"5.2","tagList":["TV","原创","战斗","穿越","WITSTUDIO","2024年7月","异世界","美漫","2024","dc","長月達平","奇幻","日本动画","搞笑","2024年","TVA","梅原裕一郎","天野明","2020-2029","长田绘里"],"aliasList":["异世界自杀突击队","异世界自杀特攻","X特遣队的奇幻之旅","Suicide Squad ISEKAI"]},{"id":"443931","alistPath":"https://bangumi.sakiko.top/Bangumi/黄昏光影","bgmUrl":"https://bangumi.tv/subject/443931","img":"//lain.bgm.tv/r/400/pic/cover/l/75/82/443931_E6OC7.jpg","name":"黄昏アウトフォーカス","chineseName":"黄昏光影","episode":"12","date":"2024年7月4日","weekday":"星期四","score":"5.4","tagList":["TV","BL","漫画改","2024年7月","校园","studiodeen","漫改","耽美","2024","松岡禎丞","内田雄馬","恋爱","青春","スタジオディーン","2024年","腐向","日常","2020s","可独立观赏","5","漫画改编","女性向","日本动画"],"aliasList":["黄昏失焦","Tasogare Out Focus","Twilight Out of Focus"]},{"id":"428823","alistPath":"https://bangumi.sakiko.top/Bangumi/疑似后宫","bgmUrl":"https://bangumi.tv/subject/428823","img":"//lain.bgm.tv/r/400/pic/cover/l/0c/fd/428823_vuwNR.jpg","name":"疑似ハーレム","chineseName":"疑似后宫","episode":"12","date":"2024年7月4日","weekday":"星期四","score":"6.2","tagList":["校园","TV","恋爱","漫画改","2024年7月","早見沙織","纯爱","NOMAD","日常","漫改","2024","岡本信彦","搞笑","2024年","2023","早见沙织","狗粮","2023年4月","日本动画","声优","日本"],"aliasList":["百变的七仓同学","模擬後宮體驗","Giji Harem"]},{"id":"425988","alistPath":"https://bangumi.sakiko.top/Bangumi/前辈是男孩子","bgmUrl":"https://bangumi.tv/subject/425988","img":"//lain.bgm.tv/r/400/pic/cover/l/53/76/425988_RH9UK.jpg","name":"先輩はおとこのこ","chineseName":"前辈是男孩子","episode":"12","date":"2024年7月4日","weekday":"星期四","score":"6.3","tagList":["校园","TV","恋爱","漫画改","2024年7月","projectNo.9","伪娘","2024","漫改","百合","柳伸亮","日常","BL","搞笑","2024年","青春","扭曲","胃疼","未定档","治愈","未确定","日本","追番"],"aliasList":["学姐是男孩","前辈是伪娘","Senpai wa Otokonoko","Senpai Is an Otokonoko"]},{"id":"450586","alistPath":"https://bangumi.sakiko.top/Bangumi/地下城里的人们","bgmUrl":"https://bangumi.tv/subject/450586","img":"//lain.bgm.tv/r/400/pic/cover/l/32/fd/450586_E67D6.jpg","name":"ダンジョンの中のひと","chineseName":"地下城里的人们","episode":"12","date":"2024年7月5日","weekday":"星期五","score":"6.5","tagList":["TV","日本","奇幻","漫画改","日常","2024年7月","异世界","OLM","轻百合","2024","百合","漫改","搞笑","TVA","职场","战斗","2024年","治愈","轻百","萌","山井纱也香","鈴代紗弓"],"aliasList":["地下城中的人","Dungeon no Naka no Hito","Dungeon People"]},{"id":"425890","alistPath":"https://bangumi.sakiko.top/Bangumi/这个世界漏洞百出","bgmUrl":"https://bangumi.tv/subject/425890","img":"//lain.bgm.tv/r/400/pic/cover/l/97/5c/425890_4dXnI.jpg","name":"この世界は不完全すぎる","chineseName":"这个世界漏洞百出","episode":"13","date":"2024年7月5日","weekday":"星期五","score":"5.5","tagList":["TV","日本","冒险","穿越","2024年7月","异世界","漫画改","奇幻","StudioPalette","2024","漫改","搞笑","网游","2024年4月","战斗","石川界人","2024年","游戏","日常","TVA","日本动画","动画","100studio"],"aliasList":["Quality Assurance in Another World","Kono Sekai wa Fukanzen Sugiru"]},{"id":"478684","alistPath":"https://bangumi.sakiko.top/Bangumi/天穗之咲稻姬","bgmUrl":"https://bangumi.tv/subject/478684","img":"//lain.bgm.tv/r/400/pic/cover/l/e9/f4/478684_gVp0X.jpg","name":"天穂のサクナヒメ","chineseName":"天穗之咲稻姬","episode":"13","date":"2024年7月6日","weekday":"星期六","score":"6.4","tagList":["TV","奇幻","游戏改","P.A.WORKS","2024年7月","花田十辉","种田","2024","神话","日常","花田十輝","2024年","战斗","游改","轻小说改","搞笑","日本","百合","日本动画","治愈","萝莉","异世界","游戏","吉原正行","大空直美"],"aliasList":["てんすいのサクナヒメ","天穗之佐久名比命","天穗之佐久名姬","Tensui no Sakuna-hime","Sakuna: Of Rice and Ruin"]},{"id":"474906","alistPath":"https://bangumi.sakiko.top/Bangumi/小市民系列","bgmUrl":"https://bangumi.tv/subject/474906","img":"//lain.bgm.tv/r/400/pic/cover/l/e2/f4/474906_z0h44.jpg","name":"小市民シリーズ","chineseName":"小市民系列","episode":"10","date":"2024年7月6日","weekday":"星期六","score":"6.2","tagList":["TV","日本","推理","日常","小说改","2024年7月","米泽穗信","LapinTrack","校园","轻小说改","2024","轻改","恋爱","羊宮妃那","神户守","悬疑","2024年","季番","TVA","青春","神戸守"],"aliasList":["How to Become Ordinary","Shoushimin Series"]},{"id":"475354","alistPath":"https://bangumi.sakiko.top/Bangumi/物语系列外传季怪物季","bgmUrl":"https://bangumi.tv/subject/475354","img":"//lain.bgm.tv/r/400/pic/cover/l/85/c1/475354_7IrYy.jpg","name":"〈物語〉シリーズ オフ&amp;モンスターシーズン","chineseName":"物语系列 外传季&amp;怪物季","episode":"15","date":"2024年7月6日","weekday":"星期六","score":"8.6","tagList":["奇幻","小说改","WEB","物语系列","SHAFT","新房昭之","2024年7月","西尾維新","轻小说改","TV","2024","轻改","Aniplex","西尾维新","2024年","后宫","续作","恋爱","神作","搞笑","物语","未定档","青春","校园","TVA","日常","早见沙织","吉澤翠","吉泽翠"],"aliasList":["物语系列 第外季&amp;第怪季","物语系列 Off&amp;Monster季","物语系列 Off&amp;Monster Season","Monogatari Series: Off &amp; Monster Season"]},{"id":"424573","alistPath":"https://bangumi.sakiko.top/Bangumi/擅长逃跑的殿下","bgmUrl":"https://bangumi.tv/subject/424573","img":"//lain.bgm.tv/r/400/pic/cover/l/32/14/424573_YYLzT.jpg","name":"逃げ上手の若君","chineseName":"擅长逃跑的殿下","episode":"12","date":"2024年7月6日","weekday":"星期六","score":"7.1","tagList":["搞笑","TV","日本","奇幻","漫画改","战斗","猎奇","历史","CloverWorks","2024年7月","梅原翔太","正太","漫改","2024","中村悠一","2024年","热血","战争","剧情","TVA","作画","萝莉","山崎雄太","松井優征"],"aliasList":["Nige Jouzu no Wakagimi","The Elusive Samurai","少主溜得快"]},{"id":"477207","alistPath":"https://bangumi.sakiko.top/Bangumi/深夜重拳","bgmUrl":"https://bangumi.tv/subject/477207","img":"//lain.bgm.tv/r/400/pic/cover/l/0c/cf/477207_0lA1U.jpg","name":"真夜中ぱんチ","chineseName":"深夜重拳","episode":"12","date":"2024年7月8日","weekday":"星期一","score":"7.4","tagList":["TV","日本","原创","P.A.WORKS","2024年7月","搞笑","百合","无法预测的命运之舞台","2024","奇幻","吸血鬼","日常","轻百合","职场","2024年","羊宮妃那","偶像","TVA","本间修","白坂英晃","本間修"],"aliasList":["深夜 Punch","深夜中的一击","深夜冲击","Mayonaka Punch"]},{"id":"464561","alistPath":"https://bangumi.sakiko.top/Bangumi/亦叶亦花","bgmUrl":"https://bangumi.tv/subject/464561","img":"//lain.bgm.tv/r/400/pic/cover/l/d5/89/464561_DRdV0.jpg","name":"菜なれ花なれ","chineseName":"亦叶亦花","episode":"12","date":"2024年7月7日","weekday":"星期日","score":"5.3","tagList":["校园","青春","TV","日本","原创","运动","日常","P.A.WORKS","2024年7月","百合","2024","轻百合","綾奈ゆにこ","2024年","超能力","无法预测的命运之舞台","励志","搞笑","2020s","少女","季番","柿本广大","关口可奈味","绫奈由仁子","柿本広大"],"aliasList":["少女如草花绽放","变成菜变成花","菜一般花一般","Narenare -Cheer for You!-","Na Nare Hana Nare"]},{"id":"479477","alistPath":"https://bangumi.sakiko.top/Bangumi/杖与剑的魔剑谭","bgmUrl":"https://bangumi.tv/subject/479477","img":"//lain.bgm.tv/r/400/pic/cover/l/6d/e5/479477_19844.jpg","name":"杖と剣のウィストリア","chineseName":"杖与剑的魔剑谭","episode":"12","date":"2024年7月7日","weekday":"星期日","score":"6.1","tagList":["热血","日本","战斗","2024年7月","奇幻","BNPictures","漫画改","TV","异世界","轻小说改","2024","Actas","漫改","轻改","厕纸","校园","龙傲天","魔法","恋爱","2024年","作画","TVA","吉原达矢","吉原達矢"],"aliasList":["Tsue to Tsurugi no Wistoria","Wistoria: Wand and Sword"]},{"id":"368116","alistPath":"https://bangumi.sakiko.top/Bangumi/尼尔‛：自动人形%20Ver1%201a%20第2部分","bgmUrl":"https://bangumi.tv/subject/368116","img":"//lain.bgm.tv/r/400/pic/cover/l/da/43/368116_fM4z8.jpg","name":"NieR: Automata Ver1.1a","chineseName":"尼尔：自动人形 Ver1.1a","episode":"12","date":"2023年1月7日","weekday":"星期六","score":"6.7","tagList":["科幻","TV","战斗","游戏改","A-1Pictures","2023年1月","尼尔","2023","花江夏樹","催泪","日本动画","2023年","石川由依","游改","末世","日本","A-1_Pictures","动画","废土","SF","奇幻","TVA","A-1","悠木碧","表番","横尾太郎","益山亮司","2B"],"aliasList":["尼尔 自动人形","尼尔 机械纪元","ニーア オートマタ"]},{"id":"446618","alistPath":"https://bangumi.sakiko.top/Bangumi/尼尔‛：自动人形%20Ver1%201a%20第2部分","bgmUrl":"https://bangumi.tv/subject/446618","img":"//lain.bgm.tv/r/400/pic/cover/l/62/d8/446618_42Up5.jpg","name":"NieR:Automata Ver1.1a 第2クール","chineseName":"尼尔：自动人形 Ver1.1a 第2部分","episode":"12","date":"2024年7月5日","weekday":"星期五","score":"6.8","tagList":["科幻","TV","战斗","游戏改","A-1Pictures","2024年7月","2024","尼尔","石川由依","日本动画","日本","2024年","末世","续作","2024年1月","致郁","A-1_Pictures","花江夏樹","SF","追番","催泪","A-1","TVA","奇幻","2020-2029","NieR:Automata","益山亮司"],"aliasList":["NieR:Automata Ver1.1a 2nd Season","NieR:Automata Ver1.1a (2024)","尼尔 自动人形 第2部分","尼尔 机械纪元 第2部分","ニーア オートマタ 第2クール"]},{"id":"464376","alistPath":"https://bangumi.sakiko.top/Bangumi/败犬女主太多了！","bgmUrl":"https://bangumi.tv/subject/464376","img":"//lain.bgm.tv/r/400/pic/cover/l/e4/dc/464376_NsZRw.jpg","name":"負けヒロインが多すぎる！","chineseName":"败犬女主太多了！","episode":"12","date":"2024年7月13日","weekday":"星期六","score":"8.1","tagList":["校园","青春","TV","恋爱","日本","小说改","A-1Pictures","2024年7月","轻小说改","败犬","搞笑","轻改","2024","日常","2024年","党争","恋爱喜剧","后宫","喜剧","治愈","动画","2020s","季番","神作","剧情","北村翔太郎","雨森たきび"],"aliasList":["败北女角太多了！","Make Heroine ga Oosugiru!","Toooooo Many Losing Heroines!"]},{"id":"465884","alistPath":"https://bangumi.sakiko.top/Bangumi/魔法少女与恶曾是敌人。","bgmUrl":"https://bangumi.tv/subject/465884","img":"//lain.bgm.tv/r/400/pic/cover/l/c9/4f/465884_z6SaK.jpg","name":"かつて魔法少女と悪は敵対していた。","chineseName":"魔法少女与邪恶曾经敌对。","episode":"12","date":"2024年7月9日","weekday":"星期二","score":"7.0","tagList":["搞笑","魔法少女","TV","恋爱","奇幻","漫画改","日常","2024年7月","BONES","2024","漫改","乙女向","綾奈ゆにこ","泡面番","中原麻衣","治愈","纯爱","2024年","狗粮","日本","6分","乙女","藤原ここあ","半原创","大橋明代"],"aliasList":["魔法少女与恶曾是敌人。","曾经、魔法少女和邪恶相互为敌。","Katsute Mahou Shoujo to Aku wa Tekitai Shite Ita.","The Magical Girl and the Evil Lieutenant Used to Be Archenemies"]},{"id":"416320","alistPath":"https://bangumi.sakiko.top/Bangumi/身为VTuber的我因为忘记关台而成了传说","bgmUrl":"https://bangumi.tv/subject/416320","img":"//lain.bgm.tv/r/400/pic/cover/l/fb/28/416320_Iprrq.jpg","name":"VTuberなんだが配信切り忘れたら伝説になってた","chineseName":"身为VTuber的我因为忘记关台而成了传说","episode":"12","date":"2024年7月7日","weekday":"星期日","score":"5.4","tagList":["吐槽","搞笑","百合","TV","日本","小说改","职业","2024年7月","轻小说改","佐倉綾音","偶像","TNK","2024","轻改","日本动画","日常","2023年","2024年","轻百合","动画","小说改编","vtuber","朝冈卓矢"],"aliasList":["VTuber Nanda ga Haishin Kiriwasuretara Densetsu ni Natteta","VTuber Legend: How I Went Viral After Forgetting to Turn Off My Stream"]},{"id":"467811","alistPath":"https://bangumi.sakiko.top/Bangumi/异世界悠闲纪行 ～边养娃边当冒险者～","bgmUrl":"https://bangumi.tv/subject/467811","img":"//lain.bgm.tv/r/400/pic/cover/l/6c/36/467811_WRG0r.jpg","name":"異世界ゆるり紀行 ～子育てしながら冒険者します～","chineseName":"异世界悠闲纪行 ～边养娃边当冒险者～","episode":"12","date":"2024年7月7日","weekday":"星期日","score":"4.1","tagList":["TV","日本","异世界","2024年7月","轻小说改","奇幻","2024","轻改","厕纸","养女儿","EMT2","战斗","日常","2024年","a.Anime","EMT","EMTSquared","鈴木愛奈"],"aliasList":["A Journey Through Another World: Raising Kids While Adventuring","Isekai Yururi Kikou: Kosodate Shinagara Boukensha Shimasu"]},{"id":"490824","alistPath":"https://bangumi.sakiko.top/Bangumi/哎咕岛消失的舔甜歌姬","bgmUrl":"https://bangumi.tv/subject/490824","img":"//lain.bgm.tv/r/400/pic/cover/l/9f/21/490824_8oJpo.jpg","name":"エグミレガシー","chineseName":"哎咕岛消失的舔甜歌姬","episode":"12","date":"2024年7月9日","weekday":"星期二","score":"6.9","tagList":["搞笑","悬疑","TV","日本","奇幻","原创","猎奇","抽象","2024年7月","泡面番","无法预测的命运之舞台","2024","江口拓也","电波","3D","沙雕","恋爱","游戏改","TVA","20年代","动画","泡面","青山吉能","StudioOutrigger"],"aliasList":["Egumi Legacy"]},{"id":"495562","alistPath":"https://bangumi.sakiko.top/Bangumi/DDDD 恶魔的破坏","bgmUrl":"https://bangumi.tv/subject/495562","img":"//lain.bgm.tv/r/400/pic/cover/l/f5/85/495562_onpMR.jpg","name":"デッドデッドデーモンズデデデデデストラクション","chineseName":"DDDD 恶魔的破坏","episode":"18","date":"2024年5月24日","weekday":"星期五","score":"7.7","tagList":["科幻","吐槽","青春","日本","漫画改","日常","剧情","WEB","Production+h.","2024","末世","2024年4月","漫改","TV","吉田玲子","百合","2024年7月","电波","2024年","奇幻","世界系","轮回","校园","SF","黒川智之","浅野一二〇","2024年5月"],"aliasList":["恶魔的破坏 DEAD DEAD DEMON'S DEDEDEDE DESTRUCTION","DEAD DEAD DEMONS DEDEDEDE DESTRUCTION"]},{"id":"391496","alistPath":"https://bangumi.sakiko.top/Bangumi/异世界失格","bgmUrl":"https://bangumi.tv/subject/391496","img":"//lain.bgm.tv/r/400/pic/cover/l/51/3f/391496_5G4nn.jpg","name":"異世界失格","chineseName":"异世界失格","episode":"12","date":"2024年7月9日","weekday":"星期二","score":"5.6","tagList":["搞笑","TV","日本","奇幻","漫画改","战斗","冒险","穿越","异世界","2024年7月","AtelierPontdarc","漫改","太宰治","神谷浩史","2024","日本动画","后宫","2024年","厕纸","反套路","轻小说改","可独立观赏","f.日本","a.Anime"],"aliasList":["Isekai Shikkaku","No Longer Allowed In Another World"]},{"id":"445722","alistPath":"https://bangumi.sakiko.top/Bangumi/恋爱没法用双子除尽","bgmUrl":"https://bangumi.tv/subject/445722","img":"//lain.bgm.tv/r/400/pic/cover/l/88/cd/445722_8A9Gy.jpg","name":"恋は双子で割り切れない","chineseName":"恋爱没法用双子除尽","episode":"12","date":"2024年7月10日","weekday":"星期三","score":"5.6","tagList":["校园","TV","恋爱","日本","日常","小说改","2024年7月","轻小说改","扭曲","2024","轻改","幼驯染","百合","党争","横手美智子","日本动画","内田真礼","姐妹","TVA","小说改编","恋爱喜剧","2024年","后宫","ROLL2"],"aliasList":["恋分双子","恋爱无法用双子除尽","双子无法用恋爱除尽","双生恋情密不可分","无法割舍恋情的双胞胎","Koi wa Futago de Warikirenai","Love Is Indivisible by Twins"]}]